LICENSE
aws_lambda_requests_wrapper/__init__.py
aws_lambda_requests_wrapper/lambda_handler.py
aws_lambda_requests_wrapper/models.py
aws_lambda_requests_wrapper/py.typed
aws_lambda_requests_wrapper-0.2.3.dist-info/LICENSE
aws_lambda_requests_wrapper-0.2.3.dist-info/WHEEL
aws_lambda_requests_wrapper-0.2.3.dist-info/METADATA
aws_lambda_requests_wrapper-0.2.3.dist-info/RECORD
