Metadata-Version: 2.1
Name: aws-lambda-requests-wrapper
Version: 0.2.3
Summary: Request/Response wrapper for AWS Lambda with API Gateway
Home-page: https://github.com/DeveloperRSquared/aws-lambda-requests-wrapper
License: MIT
Keywords: python,python3,aws,lambda,http,api-gateway,serverless,development
Author: rikhilrai
Requires-Python: >=3.7,<4.0
Classifier: Development Status :: 5 - Production/Stable
Classifier: Intended Audience :: Developers
Classifier: License :: OSI Approved :: MIT License
Classifier: Operating System :: OS Independent
Classifier: Programming Language :: Python
Classifier: Programming Language :: Python :: 3
Classifier: Programming Language :: Python :: 3.10
Classifier: Programming Language :: Python :: 3.7
Classifier: Programming Language :: Python :: 3.8
Classifier: Programming Language :: Python :: 3.9
Classifier: Topic :: Software Development :: Build Tools
Classifier: Topic :: Software Development :: Libraries :: Python Modules
Classifier: Typing :: Typed
Requires-Dist: case-insensitive-dictionary (>=0.1.1,<0.2.0)
Requires-Dist: datetime-helpers (>=0.0.14,<0.0.15)
Requires-Dist: importlib-metadata (<4.3); python_version < "3.8"
Requires-Dist: pydantic (>=1.9.0,<2.0.0)
Project-URL: Repository, https://github.com/DeveloperRSquared/aws-lambda-requests-wrapper
